magicproxy/__init__.py
magicproxy/__main__.py
magicproxy/_version.py
magicproxy/async_proxy.py
magicproxy/config.py
magicproxy/crypto.py
magicproxy/headers.py
magicproxy/keys.py
magicproxy/magictoken.py
magicproxy/plugins.py
magicproxy/proxy.py
magicproxy/queries.py
magicproxy/scopes.py
magicproxy/types.py
magic_api_proxy-0.1.14.dist-info/LICENSE
magic_api_proxy-0.1.14.dist-info/METADATA
magic_api_proxy-0.1.14.dist-info/WHEEL
magic_api_proxy-0.1.14.dist-info/top_level.txt
magic_api_proxy-0.1.14.dist-info/RECORD
