Metadata-Version: 2.1
Name: magic-api-proxy
Version: 0.1.14
Summary: A stateless API proxy
Home-page: https://github.com/rienafairefr/magic-api-proxy
Author: adapted from Alethea Katherine Flowers
Author-email: matthieu@mmea.fr
Project-URL: Bug Reports, https://github.com/rienafairefr/magic-api-proxy/issues
Project-URL: Source, https://github.com/rienafairefr/magic-api-proxy
Keywords: api github proxy
Classifier: Development Status :: 3 - Alpha
Classifier: Intended Audience :: Developers
Classifier: License :: OSI Approved :: Apache Software License
Classifier: Programming Language :: Python :: 3.6
Classifier: Programming Language :: Python :: 3.7
Requires-Python: >=3.6
License-File: LICENSE
Requires-Dist: google-auth
Requires-Dist: flask
Requires-Dist: cryptography
Requires-Dist: attrs
Requires-Dist: requests
Requires-Dist: aiohttp
Requires-Dist: pyopenssl
